MANIFEST.in
setup.py
crszu/__init__.py
crszu/cr.py
crszu/edge_detection.py
crszu/errors.py
crszu/match.py
crszu/rmnoise.py
crszu.egg-info/PKG-INFO
crszu.egg-info/SOURCES.txt
crszu.egg-info/dependency_links.txt
crszu.egg-info/requires.txt
crszu.egg-info/top_level.txt
crszu/images/captcha/gencheckcode.png
crszu/images/captcha/gencheckcode1.png
crszu/images/captcha/gencheckcode10.png
crszu/images/captcha/gencheckcode11.png
crszu/images/captcha/gencheckcode2.png
crszu/images/captcha/gencheckcode3.png
crszu/images/captcha/gencheckcode4.png
crszu/images/captcha/gencheckcode5.png
crszu/images/captcha/gencheckcode6.png
crszu/images/captcha/gencheckcode7.png
crszu/images/captcha/gencheckcode8.png
crszu/images/captcha/gencheckcode9.png
crszu/images/crops/char0.png
crszu/images/crops/char1.png
crszu/images/crops/char2.png
crszu/images/crops/char3.png
crszu/images/models/2-0.png
crszu/images/models/2-1.png
crszu/images/models/2-2.png
crszu/images/models/2-3.png
crszu/images/models/3-0.png
crszu/images/models/3-1.png
crszu/images/models/3-2.png
crszu/images/models/3-3.png
crszu/images/models/3-4.png
crszu/images/models/4-0.png
crszu/images/models/4-1.png
crszu/images/models/5-0.png
crszu/images/models/5-1.png
crszu/images/models/5-2.png
crszu/images/models/5-3.png
crszu/images/models/6-0.png
crszu/images/models/6-1.png
crszu/images/models/6-2.png
crszu/images/models/6-3.png
crszu/images/models/6-4.png
crszu/images/models/8-0.png
crszu/images/models/8-1.png
crszu/images/models/8-2.png
crszu/images/models/8-3.png
crszu/images/models/8-4.png
crszu/images/models/8-5.png
crszu/images/models/9-0.png
crszu/images/models/9-1.png
crszu/images/models/9-2.png
crszu/images/models/A-0.png
crszu/images/models/A-1.png
crszu/images/models/B-0.png
crszu/images/models/B-1.png
crszu/images/models/B-2.png
crszu/images/models/B-3.png
crszu/images/models/B-4.png
crszu/images/models/C-0.png
crszu/images/models/C-1.png
crszu/images/models/C-2.png
crszu/images/models/D-0.png
crszu/images/models/D-1.png
crszu/images/models/D-2.png
crszu/images/models/D-3.png
crszu/images/models/E-0.png
crszu/images/models/E-1.png
crszu/images/models/E-2.png
