Metadata-Version: 1.0
Name: crszu
Version: 0.0.1
Summary: captcha regonization for SZU authentication.
Home-page: https://github.com/marknv/crszu
Author: MarkNV
Author-email: marknv1991@gmail.com
License: MIT License
Platform: UNKNOWN
